tech_sentiment_analyzer/__init__.py
tech_sentiment_analyzer/main.py
tech_sentiment_analyzer/prompts.py
tech_sentiment_analyzer-2025.12.21152823.dist-info/METADATA
tech_sentiment_analyzer-2025.12.21152823.dist-info/WHEEL
tech_sentiment_analyzer-2025.12.21152823.dist-info/top_level.txt
tech_sentiment_analyzer-2025.12.21152823.dist-info/RECORD
