Metadata-Version: 2.4
Name: tech-sentiment-analyzer
Version: 2025.12.21152823
Summary: A new package that analyzes text input to determine sentiment intensity and polarity toward specific tech CEOs or companies, returning structured scores and rankings. It uses pattern matching to ensur
Author-email: tech-sentiment-analyzer <hi@eugene.plus>
License: MIT
Project-URL: Homepage, https://github.com/chigwell/tech-sentiment-analyzer
Requires-Python: >=3.9
Requires-Dist: langchain-llm7>=0.0.0
Requires-Dist: llmatch-messages>=0.0.0
Requires-Dist: langchain-core>=0.3.0
